ofxstatement_latvian-1.6.0-py3.12-nspkg.pth
ofxstatement/plugins/citadeleLV.py
ofxstatement/plugins/dnbLV.py
ofxstatement/plugins/sebLV.py
ofxstatement/plugins/swedbankLV.py
ofxstatement/plugins/swedbankLVFiDAViSta.py
ofxstatement_latvian-1.6.0.dist-info/LICENSE.md
ofxstatement_latvian-1.6.0.dist-info/METADATA
ofxstatement_latvian-1.6.0.dist-info/WHEEL
ofxstatement_latvian-1.6.0.dist-info/entry_points.txt
ofxstatement_latvian-1.6.0.dist-info/namespace_packages.txt
ofxstatement_latvian-1.6.0.dist-info/top_level.txt
ofxstatement_latvian-1.6.0.dist-info/zip-safe
ofxstatement_latvian-1.6.0.dist-info/RECORD
