Metadata-Version: 2.1
Name: ofxstatement-latvian
Version: 1.6.0
Summary: Statement parsers for banks operating in Latvia
Home-page: https://github.com/gintsmurans/ofxstatement-latvian
Author: Gints Murans
Author-email: gm@gm.lv
License: GPLv3
Keywords: ofx,ofxstatement,banking,statement,latvia
Classifier: Development Status :: 5 - Production/Stable
Classifier: Programming Language :: Python :: 3
Classifier: Natural Language :: English
Classifier: Topic :: Office/Business :: Financial :: Accounting
Classifier: Topic :: Utilities
Classifier: Environment :: Console
Classifier: Operating System :: OS Independent
Classifier: License :: OSI Approved :: GNU General Public License v3 (GPLv3)
License-File: LICENSE.md
Requires-Dist: ofxstatement
